flatgrep/__init__.py
flatgrep/loading.py
flatgrep/main.py
flatgrep-0.3.dist-info/METADATA
flatgrep-0.3.dist-info/WHEEL
flatgrep-0.3.dist-info/entry_points.txt
flatgrep-0.3.dist-info/licenses/LICENSE
flatgrep-0.3.dist-info/RECORD
