Metadata-Version: 2.4
Name: flatgrep
Version: 0.3
Summary: Quicky interact with flatpak cli
Author-email: Rodolfo Franca <souzafrodolfo@gmail.com>
License: Copyright (c) 2025 Rodolfo Souza
License-File: LICENSE
Requires-Python: >=3.13
Requires-Dist: pyfzf==0.3.1
Requires-Dist: pyperclip==1.9.0
Requires-Dist: rich==14.1.0
